[
  {
    "active": true,
    "description": "1Password password manager database file",
    "regex": "\\.agilekeychain$",
    "sectionsToMatch": ["req_url"]
  },
  {
    "active": true,
    "description": "ASP configuration file",
    "regex": "\\.asa$",
	"sectionsToMatch": ["req_url"]
  },
  {
    "active": true,
    "description": "Apple Keychain database file",
    "regex": "\\.keychain$",
	"sectionsToMatch": ["req_url"]
  },
  {
    "active": true,
    "description": "Azure service configuration schema file",
    "regex": "\\.cscfg$",
	"sectionsToMatch": ["req_url"]
  },
  {
    "active": true,
    "description": "Backup file",
    "regex": "\\.bak$",
	"sectionsToMatch": ["req_url"]
  },
  {
    "active": true,
    "description": "Certificate file",
    "regex": "\\.cer$",
	"sectionsToMatch": ["req_url"]
  },
  {
    "active": true,
    "description": "Certificate file",
    "regex": "\\.crt$",
	"sectionsToMatch": ["req_url"]
  },
  {
    "active": true,
    "description": "Certificate file",
    "regex": "\\.p7b$",
	"sectionsToMatch": ["req_url"]
  },
  {
    "active": true,
    "description": "Compressed archive file",
    "regex": "\\.zip$",
	"sectionsToMatch": ["req_url"]
  },
  {
    "active": true,
    "description": "Compressed archive file",
    "regex": "\\.tar$",
	"sectionsToMatch": ["req_url"]
  },
  {
    "active": true,
    "description": "Compressed archive file",
    "regex": "\\.gz$",
	"sectionsToMatch": ["req_url"]
  },
  {
    "active": true,
    "description": "Compressed archive file",
    "regex": "\\.tgz$",
	"sectionsToMatch": ["req_url"]
  },
  {
    "active": true,
    "description": "Compressed archive file",
    "regex": "\\.rar$",
	"sectionsToMatch": ["req_url"]
  },
  {
    "active": true,
    "description": "Configuration file",
    "regex": "\\.config$",
	"sectionsToMatch": ["req_url"]
  },
  {
    "active": true,
    "description": "Day One journal file",
    "regex": "\\.dayone$",
	"sectionsToMatch": ["req_url"]
  },
  {
    "active": true,
    "description": "Document file",
    "regex": "\\.docx$",
	"sectionsToMatch": ["req_url"]
  },
  {
    "active": true,
    "description": "Document file",
    "regex": "\\.doc$",
	"sectionsToMatch": ["req_url"]
  },
  {
    "active": true,
    "description": "Document file",
    "regex": "\\.rtf$",
	"sectionsToMatch": ["req_url"]
  },
  {
    "active": true,
    "description": "Excel file",
    "regex": "\\.xlsx$",
	"sectionsToMatch": ["req_url"]
  },
  {
    "active": true,
    "description": "Excel file",
    "regex": "\\.xls$",
	"sectionsToMatch": ["req_url"]
  },
  {
    "active": true,
    "description": "Excel file",
    "regex": "\\.csv$",
	"sectionsToMatch": ["req_url"]
  },
  {
    "active": true,
    "description": "GnuCash database file",
    "regex": "\\.gnucash$",
	"sectionsToMatch": ["req_url"]
  },
  {
    "active": true,
    "description": "Include file",
    "regex": "\\.inc$",
	"sectionsToMatch": ["req_url"]
  },
  {
    "active": true,
    "description": "Java file",
    "regex": "\\.java$",
	"sectionsToMatch": ["req_url"]
  },
  {
    "active": true,
    "description": "Java keystore file",
    "regex": "\\.jks$",
	"sectionsToMatch": ["req_url"]
  },
  {
    "active": true,
    "description": "KDE Wallet Manager database file",
    "regex": "\\.kwallet$",
	"sectionsToMatch": ["req_url"]
  },
  {
    "active": true,
    "description": "Little Snitch firewall configuration file",
    "regex": "\\.xpl$",
	"sectionsToMatch": ["req_url"]
  },
  {
    "active": true,
    "description": "Log file",
    "regex": "\\.log$",
	"sectionsToMatch": ["req_url"]
  },
  {
    "active": true,
    "description": "Microsoft BitLocker Trusted Platform Module password file",
    "regex": "\\.tpm$",
	"sectionsToMatch": ["req_url"]
  },
  {
    "active": true,
    "description": "Microsoft BitLocker recovery key file",
    "regex": "\\.bek$",
	"sectionsToMatch": ["req_url"]
  },
  {
    "active": true,
    "description": "Microsoft SQL database file",
    "regex": "\\.mdf$",
	"sectionsToMatch": ["req_url"]
  },
  {
    "active": true,
    "description": "Microsoft SQL server compact database file",
    "regex": "\\.sdf$",
	"sectionsToMatch": ["req_url"]
  },
  {
    "active": true,
    "description": "Network traffic capture file",
    "regex": "\\.pcap$",
	"sectionsToMatch": ["req_url"]
  },
  {
    "active": true,
    "description": "Old file",
    "regex": "\\.old$",
	"sectionsToMatch": ["req_url"]
  },
  {
    "active": true,
    "description": "OpenVPN client configuration file",
    "regex": "\\.ovpn$",
	"sectionsToMatch": ["req_url"]
  },
  {
    "active": true,
    "description": "PDF file",
    "regex": "\\.pdf$",
	"sectionsToMatch": ["req_url"]
  },
  {
    "active": true,
    "description": "PHP file",
    "regex": "\\.php$",
	"sectionsToMatch": ["req_url"]
  },
  {
    "active": true,
    "description": "Password Safe database file",
    "regex": "\\.psafe3$",
	"sectionsToMatch": ["req_url"]
  },
  {
    "active": true,
    "description": "Potential configuration file",
    "regex": "\\.yml$",
	"sectionsToMatch": ["req_url"]
  },
  {
    "active": true,
    "description": "Potential cryptographic key bundle",
    "regex": "\\.pkcs12$",
	"sectionsToMatch": ["req_url"]
  },
  {
    "active": true,
    "description": "Potential cryptographic key bundle",
    "regex": "\\.p12$",
	"sectionsToMatch": ["req_url"]
  },
  {
    "active": true,
    "description": "Potential cryptographic key bundle",
    "regex": "\\.pfx$",
	"sectionsToMatch": ["req_url"]
  },
  {
    "active": true,
    "description": "Potential cryptographic key bundle",
    "regex": "\\.asc$",
	"sectionsToMatch": ["req_url"]
  },
  {
    "active": true,
    "description": "Potential cryptographic private key",
    "regex": "\\.pem$",
	"sectionsToMatch": ["req_url"]
  },
  {
    "active": true,
    "description": "Potential private key",
    "regex": "otr.private_key$",
	"sectionsToMatch": ["req_url"]
  },
  {
    "active": true,
    "description": "Presentation file",
    "regex": "\\.pptx$",
	"sectionsToMatch": ["req_url"]
  },
  {
    "active": true,
    "description": "Presentation file",
    "regex": "\\.ppt$",
	"sectionsToMatch": ["req_url"]
  },
  {
    "active": true,
    "description": "Python file",
    "regex": "\\.py$",
	"sectionsToMatch": ["req_url"]
  },
  {
    "active": true,
    "description": "Remote Desktop connection file",
    "regex": "\\.rdp$",
	"sectionsToMatch": ["req_url"]
  },
  {
    "active": true,
    "description": "Ruby On Rails file",
    "regex": "\\.rb$",
	"sectionsToMatch": ["req_url"]
  },
  {
    "active": true,
    "description": "SQLite database file",
    "regex": "\\.sqlite$",
	"sectionsToMatch": ["req_url"]
  },
  {
    "active": true,
    "description": "SQLite3 database file",
    "regex": "\\.sqlite3$",
	"sectionsToMatch": ["req_url"]
  },
  {
    "active": true,
    "description": "Sequel Pro MySQL database manager bookmark file",
    "regex": "\\.plist$",
	"sectionsToMatch": ["req_url"]
  },
  {
    "active": true,
    "description": "Shell configuration file",
    "regex": "\\.exports$",
	"sectionsToMatch": ["req_url"]
  },
  {
    "active": true,
    "description": "Shell configuration file",
    "regex": "\\.functions$",
	"sectionsToMatch": ["req_url"]
  },
  {
    "active": true,
    "description": "Shell configuration file",
    "regex": "\\.extra$",
	"sectionsToMatch": ["req_url"]
  },
  {
    "active": true,
    "description": "Temporary file",
    "regex": "\\.tmp$",
	"sectionsToMatch": ["req_url"]
  },
  {
    "active": true,
    "description": "Terraform variable config file",
    "regex": "\\terraform.tfvars$",
	"sectionsToMatch": ["req_url"]
  },
  {
    "active": true,
    "description": "Text file",
    "regex": "\\.txt$",
	"sectionsToMatch": ["req_url"]
  },
  {
    "active": true,
    "description": "Tunnelblick VPN configuration file",
    "regex": "\\.tblk$",
	"sectionsToMatch": ["req_url"]
  },
  {
    "active": true,
    "description": "Windows BitLocker full volume encrypted data file",
    "regex": "\\.fve$",
	"sectionsToMatch": ["req_url"]
  },
  {
    "active": true,
    "description": "XML file",
    "regex": "\\.xml$",
	"sectionsToMatch": ["req_url"]
  }
]
